ath_sample_lib/__init__.py
ath_sample_lib/app.py
ath_sample_lib-0.0.1.dist-info/METADATA
ath_sample_lib-0.0.1.dist-info/WHEEL
ath_sample_lib-0.0.1.dist-info/top_level.txt
ath_sample_lib-0.0.1.dist-info/RECORD
